jupS3/__init__.py
jupS3/handlers.py
jupS3/tests/__init__.py
jupS3/tests/test_handlers.py
jups3-0.0.6.data/data/etc/jupyter/jupyter_server_config.d/jupS3.json
jups3-0.0.6.data/data/share/jupyter/labextensions/jupS3/package.json
jups3-0.0.6.data/data/share/jupyter/labextensions/jupS3/schemas/jupS3/package.json.orig
jups3-0.0.6.data/data/share/jupyter/labextensions/jupS3/schemas/jupS3/plugin.json
jups3-0.0.6.data/data/share/jupyter/labextensions/jupS3/static/675.9d13a42fbaeaec73308a.js
jups3-0.0.6.data/data/share/jupyter/labextensions/jupS3/static/728.1d053b74ed49e9aeadb1.js
jups3-0.0.6.data/data/share/jupyter/labextensions/jupS3/static/remoteEntry.3150c5b2bbe7b7e05b2a.js
jups3-0.0.6.data/data/share/jupyter/labextensions/jupS3/static/style.js
jups3-0.0.6.data/data/share/jupyter/labextensions/jupS3/static/third-party-licenses.json
jups3-0.0.6.data/data/share/jupyter/labextensions/jupS3/install.json
jups3-0.0.6.dist-info/METADATA
jups3-0.0.6.dist-info/WHEEL
jups3-0.0.6.dist-info/licenses/LICENSE
jups3-0.0.6.dist-info/RECORD
